cgd_verify/__init__.py
cgd_verify/cli.py
cgd_verify-0.1.1.dist-info/METADATA
cgd_verify-0.1.1.dist-info/WHEEL
cgd_verify-0.1.1.dist-info/entry_points.txt
cgd_verify-0.1.1.dist-info/RECORD
