Metadata-Version: 2.4
Name: cgd-verify
Version: 0.1.1
Summary: Quick verification for Clarity-Gated Document (.cgd) files - returns pass/fail for CI/CD pipelines
Project-URL: Homepage, https://github.com/frmoretto/clarity-gate
Project-URL: Repository, https://github.com/frmoretto/clarity-gate
Project-URL: Documentation, https://github.com/frmoretto/clarity-gate/blob/main/docs/FILE_FORMAT_SPEC.md
Project-URL: Issues, https://github.com/frmoretto/clarity-gate/issues
Author-email: Francesco Marinoni Moretto <francesco@fmmconsulting.it>
License-Expression: CC-BY-4.0
Keywords: ai-safety,cgd,ci-cd,clarity-gate,epistemic,llm,rag,validator,verify
Classifier: Development Status :: 3 - Alpha
Classifier: Intended Audience :: Developers
Classifier: Programming Language :: Python :: 3
Classifier: Programming Language :: Python :: 3.9
Classifier: Programming Language :: Python :: 3.10
Classifier: Programming Language :: Python :: 3.11
Classifier: Programming Language :: Python :: 3.12
Classifier: Topic :: Documentation
Classifier: Topic :: Scientific/Engineering :: Artificial Intelligence
Requires-Python: >=3.9
Requires-Dist: cgd-validator>=0.1.1
